weauth/__init__.py
weauth/__main__.py
weauth/weauth_boostrap.py
weauth/weauth_entrypoint.py
weauth/wechat_confirm.py
weauth/cdkey/__init__.py
weauth/cdkey/cdkey.py
weauth/command_line/__init__.py
weauth/command_line/admin_cli.py
weauth/command_line/command_line.py
weauth/constants/__init__.py
weauth/constants/core_constant.py
weauth/constants/exit_code.py
weauth/database/__init__.py
weauth/database/database.py
weauth/exceptions/__init__.py
weauth/exceptions/exceptions.py
weauth/listener/__init__.py
weauth/listener/listener.py
weauth/listener/wechat_confirm_listener.py
weauth/listener/wtest_listener.py
weauth/mc_server/__init__.py
weauth/mc_server/mc_server_connection.py
weauth/mc_server/mcsm_connect/__init__.py
weauth/mc_server/mcsm_connect/mcsm.py
weauth/mc_server/mcsm_connect/outputget.py
weauth/mc_server/rcon_connect/__init__.py
weauth/mc_server/rcon_connect/rcon.py
weauth/tencent_server/__init__.py
weauth/tencent_server/qq_server/__init__.py
weauth/tencent_server/wx_server/__init__.py
weauth/tencent_server/wx_server/wx_connection.py
weauth/utils/__init__.py
weauth/utils/add_op.py
weauth/utils/check_for_update.py
weauth/utils/create_config_yaml.py
weauth/utils/gtest.py
weauth/utils/wtest.py
weauth-1.6.1.dist-info/LICENSE
weauth-1.6.1.dist-info/METADATA
weauth-1.6.1.dist-info/WHEEL
weauth-1.6.1.dist-info/entry_points.txt
weauth-1.6.1.dist-info/top_level.txt
weauth-1.6.1.dist-info/RECORD
