Metadata-Version: 2.2
Name: weauth
Version: 1.6.1
Summary: A python tool to managing your whitelist through WeChat. 使用微信公众号来管理MC服务器与注册白名单。
Author: NearlyHeadlessJack
Author-email: wang@rjack.cn
License: GPLv3
Project-URL: Homepage, https://github.com/TomatoCraftMC/WeAuth
Project-URL: Documentation, https://github.com/TomatoCraftMC/WeAuth/blob/main/README.md
Classifier: License :: OSI Approved :: GNU General Public License v3 (GPLv3)
Classifier: Natural Language :: Chinese (Simplified)
Classifier: Operating System :: OS Independent
Classifier: Topic :: Utilities
Classifier: Framework :: Flask
Classifier: Programming Language :: Python
Classifier: Programming Language :: Python :: 3
Classifier: Programming Language :: Python :: 3.8
Classifier: Programming Language :: Python :: 3.9
Classifier: Programming Language :: Python :: 3.10
Classifier: Programming Language :: Python :: 3.11
Classifier: Programming Language :: Python :: 3.12
Classifier: Programming Language :: Python :: 3.13
Requires-Python: >=3.8
License-File: LICENSE
Requires-Dist: Flask>=3.0.3
Requires-Dist: PyYAML>=6.0.1
Requires-Dist: requests>=2.32.3
Requires-Dist: rcon>=2.1.1
Requires-Dist: tcping==0.1.1rc1
Requires-Dist: gevent>=24.2.1
Requires-Dist: prettytable>=0.2.13
Dynamic: author
Dynamic: author-email
Dynamic: classifier
Dynamic: description
Dynamic: description-content-type
Dynamic: license
Dynamic: project-url
Dynamic: requires-dist
Dynamic: requires-python
Dynamic: summary
